{
	"info": {
		"_postman_id": "b3f3e1d0-1234-5678-9abc-def012345678",
		"name": "Cosmic Watch API",
		"description": "API collection for the Cosmic Watch Asteroid Tracker",
		"schema": "https://schema.getpostman.com/json/collection/v2.1.0/collection.json"
	},
	"item": [
		{
			"name": "Auth",
			"item": [
				{
					"name": "Register User",
					"request": {
						"method": "POST",
						"header": [
							{
								"key": "Content-Type",
								"value": "application/json"
							}
						],
						"body": {
							"mode": "raw",
							"raw": "{\n    \"name\": \"Test Researcher\",\n    \"email\": \"test@nasa.gov\",\n    \"password\": \"password123\"\n}"
						},
						"url": {
							"raw": "http://localhost:5000/api/auth/register",
							"protocol": "http",
							"host": ["localhost"],
							"port": "5000",
							"path": ["api", "auth", "register"]
						}
					},
					"response": []
				},
				{
					"name": "Login User",
					"event": [
						{
							"listen": "test",
							"script": {
								"exec": [
									"var jsonData = pm.response.json();",
									"pm.environment.set(\"authToken\", jsonData.token);"
								],
								"type": "text/javascript"
							}
						}
					],
					"request": {
						"method": "POST",
						"header": [
							{
								"key": "Content-Type",
								"value": "application/json"
							}
						],
						"body": {
							"mode": "raw",
							"raw": "{\n    \"email\": \"test@nasa.gov\",\n    \"password\": \"password123\"\n}"
						},
						"url": {
							"raw": "http://localhost:5000/api/auth/login",
							"protocol": "http",
							"host": ["localhost"],
							"port": "5000",
							"path": ["api", "auth", "login"]
						}
					},
					"response": []
				}
			]
		},
		{
			"name": "Asteroids",
			"item": [
				{
					"name": "Get Live Feed",
					"request": {
						"method": "GET",
						"header": [],
						"url": {
							"raw": "http://localhost:5000/api/asteroids/feed",
							"protocol": "http",
							"host": ["localhost"],
							"port": "5000",
							"path": ["api", "asteroids", "feed"]
						}
					},
					"response": []
				},
				{
					"name": "Add to Watchlist (Protected)",
					"request": {
						"method": "POST",
						"header": [
							{
								"key": "Authorization",
								"value": "Bearer {{authToken}}"
							},
							{
								"key": "Content-Type",
								"value": "application/json"
							}
						],
						"body": {
							"mode": "raw",
							"raw": "{\n    \"asteroidId\": \"2465633\",\n    \"name\": \"2002 AC\"\n}"
						},
						"url": {
							"raw": "http://localhost:5000/api/asteroids/watchlist",
							"protocol": "http",
							"host": ["localhost"],
							"port": "5000",
							"path": ["api", "asteroids", "watchlist"]
						}
					},
					"response": []
				}
			]
		}
	]
}